dskit/__init__.py
dskit/frame/__init__.py
dskit/frame/frame.py
dskit/tensor/__init__.py
dskit/tensor/tensor.py
dskit-0.1.1.dist-info/LICENSE.md
dskit-0.1.1.dist-info/METADATA
dskit-0.1.1.dist-info/WHEEL
dskit-0.1.1.dist-info/top_level.txt
dskit-0.1.1.dist-info/RECORD
