Metadata-Version: 2.1
Name: dskit
Version: 0.1.1
Summary: Python Data Science Kit for Humans.
Home-page: https://bitbucket.org/shkroba/dskit
Author: Illia Shkroba
Author-email: is@pjwstk.edu.pl
License: UNKNOWN
Platform: UNKNOWN
Classifier: Intended Audience :: Developers
Classifier: Intended Audience :: Science/Research
Classifier: License :: OSI Approved :: GNU Lesser General Public License v3 (LGPLv3)
Classifier: Operating System :: OS Independent
Classifier: Programming Language :: Python :: 3.6
Classifier: Topic :: Software Development :: Libraries :: Application Frameworks
Classifier: Typing :: Typed
Requires-Python: >=3.6
License-File: LICENSE.md
Requires-Dist: nonion (>=0.4.1)
Requires-Dist: numpy (>=1.16)
Requires-Dist: pandas (>=1.1.0)
Requires-Dist: scikit-learn (>=0.24.2)
